pytextutils/__init__.py
pytextutils/core.py
pytextutils-0.1.0.dist-info/METADATA
pytextutils-0.1.0.dist-info/WHEEL
pytextutils-0.1.0.dist-info/top_level.txt
pytextutils-0.1.0.dist-info/RECORD
