Metadata-Version: 2.4
Name: pytextutils
Version: 0.1.0
Summary: Common string helpers - reverse, slugify, capitalize, remove punctuation
Author: PyLib Contributors
License: MIT
Project-URL: Homepage, https://github.com/yourusername/PyLib
Project-URL: Repository, https://github.com/yourusername/PyLib
Keywords: string,text,utilities,helpers
Classifier: Development Status :: 3 - Alpha
Classifier: Intended Audience :: Developers
Classifier: License :: OSI Approved :: MIT License
Classifier: Programming Language :: Python :: 3
Classifier: Programming Language :: Python :: 3.8
Classifier: Programming Language :: Python :: 3.9
Classifier: Programming Language :: Python :: 3.10
Classifier: Programming Language :: Python :: 3.11
Requires-Python: >=3.8
